LICENSE
MANIFEST.in
README.md
setup.py
tap_outreach/__init__.py
tap_outreach/client.py
tap_outreach/discover.py
tap_outreach/sync.py
tap_outreach.egg-info/PKG-INFO
tap_outreach.egg-info/SOURCES.txt
tap_outreach.egg-info/dependency_links.txt
tap_outreach.egg-info/entry_points.txt
tap_outreach.egg-info/requires.txt
tap_outreach.egg-info/top_level.txt
tap_outreach/schemas/accounts.json
tap_outreach/schemas/call_dispositions.json
tap_outreach/schemas/call_purposes.json
tap_outreach/schemas/calls.json
tap_outreach/schemas/content_categories.json
tap_outreach/schemas/duties.json
tap_outreach/schemas/events.json
tap_outreach/schemas/mailboxes.json
tap_outreach/schemas/mailings.json
tap_outreach/schemas/opportunities.json
tap_outreach/schemas/personas.json
tap_outreach/schemas/prospects.json
tap_outreach/schemas/sequence_states.json
tap_outreach/schemas/sequence_steps.json
tap_outreach/schemas/sequence_templates.json
tap_outreach/schemas/sequences.json
tap_outreach/schemas/stages.json
tap_outreach/schemas/tasks.json
tap_outreach/schemas/teams.json
tap_outreach/schemas/users.json
tests/test_all_fields.py
tests/test_automatic_fields.py
tests/test_bookmark.py
tests/test_discovery.py
tests/test_interrupted_sync.py
tests/test_pagination.py
tests/test_start_date.py
tests/test_sync_canary.py