Metadata-Version: 2.4
Name: tap-outreach
Version: 1.2.0
Summary: Singer.io tap for extracting data from the Outreach.io API
Home-page: https://singer.io
Author: Stitch
Classifier: Programming Language :: Python :: 3 :: Only
License-File: LICENSE
Requires-Dist: backoff==2.2.1
Requires-Dist: requests==2.32.3
Requires-Dist: singer-python==6.1.1
Provides-Extra: dev
Requires-Dist: ipdb; extra == "dev"
Requires-Dist: nose; extra == "dev"
Requires-Dist: pylint==2.6.2; extra == "dev"
Requires-Dist: requests-mock==1.9.3; extra == "dev"
Dynamic: author
Dynamic: classifier
Dynamic: home-page
Dynamic: license-file
Dynamic: provides-extra
Dynamic: requires-dist
Dynamic: summary
